backend/temp/0f248d00-3b97-4ce4-939c-d5114ebcc5f0/design.v
module fifo_async #(parameter DEPTH=16) (
  input  wr_clk, rd_clk, rst_n,
  input  wr_en, rd_en,
  input  [7:0] wr_data,
  output reg [7:0] rd_data,
  output full, empty
);
  localparam PTR = $clog2(DEPTH);
  reg [7:0] mem [0:DEPTH-1];
  reg [PTR:0] wr_ptr, rd_ptr;

  // TODO: Gray-code sync, full/empty flags

endmodule

backend/temp/0f248d00-3b97-4ce4-939c-d5114ebcc5f0/testbench.v
`timescale 1ns/1ps
module testbench;
  reg wr_clk, rd_clk, rst_n, wr_en, rd_en;
  reg [7:0] wr_data;
  wire [7:0] rd_data;
  wire full, empty;

  fifo_async #(.DEPTH(16)) dut (
    .wr_clk(wr_clk), .rd_clk(rd_clk), .rst_n(rst_n),
    .wr_en(wr_en), .rd_en(rd_en),
    .wr_data(wr_data), .rd_data(rd_data),
    .full(full), .empty(empty)
  );

  initial wr_clk = 0; always #5  wr_clk = ~wr_clk;
  initial rd_clk = 0; always #7  rd_clk = ~rd_clk;

  initial begin
    $dumpfile("sim.vcd");
    $dumpvars(0, testbench);

    rst_n=0; wr_en=0; rd_en=0; wr_data=0;
    #20; rst_n=1;

    if (empty) $display("PASS: empty after reset");
    else       $display("FAIL: expected empty after reset");

    wr_en=1;
    @(posedge wr_clk); wr_data=8'hAA;
    @(posedge wr_clk); wr_data=8'hBB;
    @(posedge wr_clk); wr_data=8'hCC;
    @(posedge wr_clk); wr_data=8'hDD;
    wr_en=0;

    #30;
    rd_en=1;
    @(posedge rd_clk); #2;
    $display("rd_data=0x%h full=%b empty=%b", rd_data, full, empty);
    @(posedge rd_clk); #2;
    rd_en=0;

    #50;
    $display("Simulation complete");
    $finish;
  end
endmodule

backend/temp/0f248d00-3b97-4ce4-939c-d5114ebcc5f0/sim.vcd
$date
	Tue Jun 23 19:06:51 2026
$end
$version
	Icarus Verilog
$end
$timescale
	1ps
$end
$scope module testbench $end
$var wire 1 ! empty $end
$var wire 1 " full $end
$var wire 8 # rd_data [7:0] $end
$var reg 1 $ rd_clk $end
$var reg 1 % rd_en $end
$var reg 1 & rst_n $end
$var reg 1 ' wr_clk $end
$var reg 8 ( wr_data [7:0] $end
$var reg 1 ) wr_en $end
$scope module dut $end
$var wire 1 ! empty $end
$var wire 1 " full $end
$var wire 1 $ rd_clk $end
$var wire 1 % rd_en $end
$var wire 1 & rst_n $end
$var wire 1 ' wr_clk $end
$var wire 8 * wr_data [7:0] $end
$var wire 1 ) wr_en $end
$var parameter 32 + DEPTH $end
$var parameter 32 , PTR $end
$var reg 8 - rd_data [7:0] $end
$upscope $end
$upscope $end
$enddefinitions $end
$comment Show the parameter values. $end
$dumpall
b100 ,
b10000 +
$end
#0
$dumpvars
bx -
b0 *
0)
b0 (
0'
0&
0%
0$
bx #
z"
z!
$end
#5000
1'
#7000
1$
#10000
0'
#14000
0$
#15000
1'
#20000
0'
1)
1&
#21000
1$
#25000
b10101010 (
b10101010 *
1'
#28000
0$
#30000
0'
#35000
b10111011 (
b10111011 *
1'
1$
#40000
0'
#42000
0$
#45000
b11001100 (
b11001100 *
1'
#49000
1$
#50000
0'
#55000
0)
b11011101 (
b11011101 *
1'
#56000
0$
#60000
0'
#63000
1$
#65000
1'
#70000
0'
0$
#75000
1'
#77000
1$
#80000
0'
#84000
0$
#85000
1'
1%
#90000
0'
#91000
1$
#95000
1'
#98000
0$
#100000
0'
#105000
1'
1$
#107000
0%
