backend/temp/e8b7d507-af3e-447c-b88c-32b981d7b76d/design.v
module full_adder (
    input  a,
    input  b,
    input  cin,
    output sum,
    output cout
);

    assign sum  = a ^ b ^ cin;
    assign cout = (a & b) | (b & cin) | (a & cin);

endmodule

backend/temp/e9c66c6d-87ae-4904-99d1-d3fe5c2c5f96/testbench.v
`timescale 1ns/1ps

module tb_full_adder;

    reg a, b, cin;
    wire sum, cout;

    // DUT Instantiation
    full_adder dut (
        .a(a),
        .b(b),
        .cin(cin),
        .sum(sum),
        .cout(cout)
    );

    // VCD Dump
    initial begin
        $dumpfile("full_adder.vcd");
        $dumpvars(0, tb_full_adder);
    end

    // Stimulus
    initial begin
        $display("Time\t a b cin | sum cout");
        $monitor("%0t\t %b %b  %b  |  %b   %b",
                  $time, a, b, cin, sum, cout);

        a=0; b=0; cin=0; #10;
        a=0; b=0; cin=1; #10;
        a=0; b=1; cin=0; #10;
        a=0; b=1; cin=1; #10;
        a=1; b=0; cin=0; #10;
        a=1; b=0; cin=1; #10;
        a=1; b=1; cin=0; #10;
        a=1; b=1; cin=1; #10;

        $finish;
    end

endmodule

backend/temp/e8b7d507-af3e-447c-b88c-32b981d7b76d/full_adder.vcd
$date
	Tue Jun 23 19:08:33 2026
$end
$version
	Icarus Verilog
$end
$timescale
	1ps
$end
$scope module tb_full_adder $end
$var wire 1 ! sum $end
$var wire 1 " cout $end
$var reg 1 # a $end
$var reg 1 $ b $end
$var reg 1 % cin $end
$scope module dut $end
$var wire 1 # a $end
$var wire 1 $ b $end
$var wire 1 % cin $end
$var wire 1 " cout $end
$var wire 1 ! sum $end
$upscope $end
$upscope $end
$enddefinitions $end
$comment Show the parameter values. $end
$dumpall
$end
#0
$dumpvars
0%
0$
0#
0"
0!
$end
#10000
1!
1%
#20000
0%
1$
#30000
1"
0!
1%
#40000
0"
1!
0%
0$
1#
#50000
1"
0!
1%
#60000
0%
1$
#70000
1!
1%
