backend/temp/74c6b506-9274-4410-b329-1380a0ebfc04/design.sv
module counter4 (
    input clk,
    input rst,
    output reg [3:0] count
);

always @(posedge clk) begin
    if (rst)
        count <= 4'b0000;
    else
        count <= count + 1'b1;
end

endmodule

backend/temp/85768e78-60b3-4507-9095-c284941d5be2/testbench.sv
module testbench;

reg clk, rst;
wire [3:0] count;

counter4 uut (
    .clk(clk),
    .rst(rst),
    .count(count)
);

initial begin
    $dumpfile("sim.vcd");
    $dumpvars(0, testbench);
end

initial begin
    clk = 0;
    forever #5 clk = ~clk;
end

initial begin
    rst = 1;
    #12 rst = 0;
    #100 $finish;
end

endmodule

backend/temp/85768e78-60b3-4507-9095-c284941d5be2/sim.vcd
$date
	Mon Jun 22 22:12:58 2026
$end
$version
	Icarus Verilog
$end
$timescale
	1s
$end
$scope module testbench $end
$var wire 4 ! count [3:0] $end
$var reg 1 " clk $end
$var reg 1 # rst $end
$scope module uut $end
$var wire 1 " clk $end
$var wire 1 # rst $end
$var reg 4 $ count [3:0] $end
$upscope $end
$upscope $end
$enddefinitions $end
$comment Show the parameter values. $end
$dumpall
$end
#0
$dumpvars
bx $
1#
0"
bx !
$end
#5
b0 !
b0 $
1"
#10
0"
#12
0#
#15
b1 !
b1 $
1"
#20
0"
#25
b10 !
b10 $
1"
#30
0"
#35
b11 !
b11 $
1"
#40
0"
#45
b100 !
b100 $
1"
#50
0"
#55
b101 !
b101 $
1"
#60
0"
#65
b110 !
b110 $
1"
#70
0"
#75
b111 !
b111 $
1"
#80
0"
#85
b1000 !
b1000 $
1"
#90
0"
#95
b1001 !
b1001 $
1"
#100
0"
#105
b1010 !
b1010 $
1"
